odoo8_addon_event_kanban_view_optimized-8.0.1.0.0.99.dev1-py2.7-nspkg.pth
odoo_addons/event_kanban_view_optimized/__openerp__.py
odoo_addons/event_kanban_view_optimized/__init__.py
odoo_addons/event_kanban_view_optimized/README.rst
odoo_addons/event_kanban_view_optimized/views/event_event_view.xml
odoo_addons/event_kanban_view_optimized/static/description/icon.png
odoo8_addon_event_kanban_view_optimized-8.0.1.0.0.99.dev1.dist-info/top_level.txt
odoo8_addon_event_kanban_view_optimized-8.0.1.0.0.99.dev1.dist-info/WHEEL
odoo8_addon_event_kanban_view_optimized-8.0.1.0.0.99.dev1.dist-info/RECORD
odoo8_addon_event_kanban_view_optimized-8.0.1.0.0.99.dev1.dist-info/metadata.json
odoo8_addon_event_kanban_view_optimized-8.0.1.0.0.99.dev1.dist-info/DESCRIPTION.rst
odoo8_addon_event_kanban_view_optimized-8.0.1.0.0.99.dev1.dist-info/METADATA
odoo8_addon_event_kanban_view_optimized-8.0.1.0.0.99.dev1.dist-info/namespace_packages.txt
